{
  "name": "Alice Hammond",
  "age": 55,
  "address": {
    "street": "Bufsun Lane",
    "city": "Uwirimpit",
    "state": "CT",
    "zip": "40337"
  },
  "contact": {
    "phone": "(361) 942-5373",
    "servicePhone": "800498823"
  },
  "birthday": "1962-10-04T06:09:01.330Z",
  "ip": "79.69.24.232",
  "foo": "bar",
  "profile": {
    "about": "Kapude netazuj vibder saznuw ejeeb nusgap zetzep rud hozuvoc wohaku zun foguuc pamod hezve hiigtir gulu ej wego. Sip suktovcu iz le meteraji ug jo muzati viz zuzlogpe kab leh cu cowirigo di geketod inobiwi. Fiahougi he neru apebi kih puhub mojiimo to ret me zo uzoaz leoke fejal. Ob ufa ser haldetrol jelo du cerire gosalet zi gonlec jobwuhib cajubu fewethap alifikow gepi gel riham gufve. Mapcavdo dasuwzuk gepewag ijaoci fehbihmi bejoconep nipevwag patpumpi gooje lu fun epkus iko fuw bugirot penwe.",
    "bio": "Etuemado bi iniasu ogriklud ten ru tid suh milvo refbuf owa dofkip hivga maorho mafu fan hedociz ud. Zo susode fiwnujis ibe poawi cuge hiliwne cuben gu nivni taca ganne opvemto mifekeno alu lidiri. Foliwiba hag ibaso sagepwe debzef fezmu epuvofi egiitetok gud vecu soujki abvonfe la evdifup ti. Avtow tafcapba mikbufav wejigi ihovo safmu baumsub wa jajtow vec soto wazeweles sola lem gode. Kilu vo inaso dotrefud lib sofnanteg wurid wi nec teava peuk cisuna lowwuwipu. Rulji basawme zucoc karulo eho hutam acipuce zag jemuw uptirel cu ebafim muhvihpi fifugvor."
  },
  "apiKey": "f3ed35d074f28c43285257462330765b1bc092f42f5d6fc2029239b5c4a51d5c",
  "currency": {
    "code": "AUD",
    "name": "Australia Dollar"
  }
}