{
  "name": "Adeline Franklin",
  "age": 39,
  "address": {
    "street": "Kegsur Highway",
    "city": "Epaehifa",
    "state": "WV",
    "zip": "73480"
  },
  "contact": {
    "phone": "(266) 390-9157",
    "servicePhone": "800747742"
  },
  "birthday": "2002-05-24T09:39:08.036Z",
  "ip": "68.251.117.144",
  "foo": "bar",
  "profile": {
    "about": "Bov honwaw edta ena gedzib fis ni ima ij luricoc win huvnuwuja ejohacvob ci. Beze vojfodmu sabu en ijuvej hezriwduc roup ib ticjo vead tibtondi kob vupezow hagom coumlo lo dog. Nagurat abadetri liteg ka izumer pitas dal isomo nu he bu dietueg aclumir nuhmajzud. Zez basnefo ime fosguke tutriiko sikubev gabaktek fujusced wehujnel dimozos bune nagpaner nih. Forozo emzombe ce im ju lirci kegnajid omma di evubec ikuwojga lucdivus apeafmo luv uzabohis nir.",
    "bio": "Oruujgu ges losor wi zog coci om gu nacvo tij timeba bo igma apu neotdi ubluhom fehfozka cehutpa. Guiho cupcag pu vimcoju ifrafve tuj cemmum obboc aduluozo bagevupo teihorum sohamu udoitfu jitja wesoz ewguz nof. Ahzut pifav kabenemil iznize azej utepeate niffe kuivlah ba huwtiwo badupa lihsu wemopeb viv pigzohib wojloz de jojbu. Wenvej cikek cimsiska nufdef tittewvo hi pizwosoz naj ej sawaza mafpu kacdizo fivne namotem pasapci."
  },
  "apiKey": "43fd9258c0bb4e28dc254aea23dc7405121b881ef9caa4250f10c5fbed566f43",
  "currency": {
    "code": "PGK",
    "name": "Papua New Guinea Kina"
  }
}